LICENSE
MANIFEST.in
README.md
adqsetup.py
setup.py
adqsetup.egg-info/PKG-INFO
adqsetup.egg-info/SOURCES.txt
adqsetup.egg-info/dependency_links.txt
adqsetup.egg-info/entry_points.txt
adqsetup.egg-info/not-zip-safe
adqsetup.egg-info/top_level.txt