Metadata-Version: 2.1
Name: adqsetup
Version: 2.0a1
Summary: A pure Python tool and library to setup ADQ for Intel NICs
Home-page: https://www.intel.com/content/www/us/en/architecture-and-technology/ethernet/adq-resource-center.html
Author: Intel
License: BSD-3-Clause
Platform: UNKNOWN
License-File: LICENSE
